[{
  "_id": {
    "$oid": "620ccae82991df4442fe1187"
  },
  "name_prov": "prov1",
  "telefon": "111111111",
  "correu_electronic": "prov1@prov1.com",
  "codiPostal": "08100",
  "ciutat": "ciutat",
  "pais": "pais"
},{
  "_id": {
    "$oid": "620ccae82991df4442fe1188"
  },
  "name_prov": "prov2",
  "telefon": "222222222",
  "correu_electronic": "prov2@prov2.com",
  "adress": "adress prov2",
  "codiPostal": "08200",
  "ciutat": "ciutat",
  "pais": "pais"
},{
  "_id": {
    "$oid": "620ce1ec2991df4442fe11f2"
  },
  "name_prov": "prov3",
  "telefon": "333333333",
  "correu_electronic": "prov3@prov3.com",
  "codiPostal": "08300",
  "ciutat": "ciutat",
  "pais": "pais"
}]